valerius/__init__.py
valerius/sequences.py
valerius/utilities.py
valerius-0.2.0.dist-info/LICENSE
valerius-0.2.0.dist-info/METADATA
valerius-0.2.0.dist-info/WHEEL
valerius-0.2.0.dist-info/top_level.txt
valerius-0.2.0.dist-info/RECORD
